IMPORT_NAME sys
IMPORT_NAME math
IMPORT_NAME cmath
IMPORT_NAME collections
IMPORT_NAME itertools
IMPORT_NAME json
IMPORT_NAME re
IMPORT_NAME asyncio
IMPORT_FROM functools
IMPORT_FROM wraps
IMPORT_FROM typing
IMPORT_FROM Any
IMPORT_FROM List
IMPORT_FROM Dict
IMPORT_FROM Tuple
IMPORT_FROM Set
IMPORT_FROM Optional
IMPORT_NAME os
IMPORT_NAME subprocess
IMPORT_NAME socket
IMPORT_NAME urllib.request
IMPORT_NAME base64
IMPORT_NAME pickle
IMPORT_NAME marshal
IMPORT_NAME types
IMPORT_NAME importlib
IMPORT_NAME tempfile
IMPORT_NAME shutil
IMPORT_NAME pathlib
IMPORT_FROM os
IMPORT_FROM environ
IMPORT_FROM path
IMPORT_FROM listdir
IMPORT_FROM sys
IMPORT_FROM argv
IMPORT_FROM exit
IMPORT_FROM modules
IMPORT_FROM path
IMPORT_FROM sys_path
IMPORT_FROM subprocess
IMPORT_FROM run
IMPORT_FROM Popen
IMPORT_FROM PIPE
IMPORT_FROM call
IMPORT_FROM socket
IMPORT_FROM socket
IMPORT_FROM AF_INET
IMPORT_FROM SOCK_STREAM
IMPORT_FROM urllib.parse
IMPORT_FROM urlparse
IMPORT_FROM urljoin
IMPORT_FROM urllib.request
IMPORT_FROM urlopen
IMPORT_FROM Request
IMPORT_FROM base64
IMPORT_FROM b64encode
IMPORT_FROM b64decode
IMPORT_FROM decodebytes
IMPORT_FROM pickle
IMPORT_FROM loads
IMPORT_FROM dumps
IMPORT_FROM load
IMPORT_FROM dump
IMPORT_FROM marshal
IMPORT_FROM loads
IMPORT_FROM marshal_loads
IMPORT_FROM dumps
IMPORT_FROM marshal_dumps
IMPORT_FROM types
IMPORT_FROM CodeType
IMPORT_FROM ModuleType
IMPORT_FROM importlib
IMPORT_FROM import_module
IMPORT_FROM util
IMPORT_FROM tempfile
IMPORT_FROM mkstemp
IMPORT_FROM mkdtemp
IMPORT_FROM NamedTemporaryFile
IMPORT_FROM shutil
IMPORT_FROM rmtree
IMPORT_FROM copytree
IMPORT_FROM move
IMPORT_FROM pathlib
IMPORT_FROM Path
IMPORT_FROM PurePath
IMPORT_NAME os
IMPORT_NAME operating_system
IMPORT_NAME subprocess
IMPORT_NAME subproc
IMPORT_NAME socket
IMPORT_NAME sock
IMPORT_NAME urllib.request
IMPORT_NAME web_request
IMPORT_NAME base64
IMPORT_NAME b64
IMPORT_NAME pickle
IMPORT_NAME pkl
IMPORT_NAME marshal
IMPORT_NAME marsh
IMPORT_NAME types
IMPORT_NAME tp
IMPORT_NAME importlib
IMPORT_NAME imp_lib
IMPORT_FROM os.path
IMPORT_FROM join
IMPORT_FROM exists
IMPORT_FROM isfile
IMPORT_FROM isdir
IMPORT_FROM basename
IMPORT_FROM dirname
IMPORT_FROM os.path
IMPORT_FROM join
IMPORT_FROM path_join
IMPORT_FROM exists
IMPORT_FROM path_exists
IMPORT_FROM urllib.request
IMPORT_FROM urlopen
IMPORT_FROM open_url
IMPORT_FROM Request
IMPORT_FROM web_request_obj
IMPORT_FROM base64
IMPORT_FROM b64encode
IMPORT_FROM encode_b64
IMPORT_FROM b64decode
IMPORT_FROM decode_b64
IMPORT_NAME ctypes
IMPORT_FROM ctypes
IMPORT_FROM windll
IMPORT_FROM wintypes
LOAD_CONST True
STORE_NAME ctypes_available
POP_TOP None
JUMP_FORWARD 9
JUMP_FORWARD 7
IMPORT_NAME win32api
IMPORT_FROM win32api
IMPORT_FROM GetSystemMetrics
LOAD_CONST True
STORE_NAME win32_available
POP_TOP None
JUMP_FORWARD 8
JUMP_FORWARD 6
IMPORT_NAME requests
IMPORT_FROM requests
IMPORT_FROM get
IMPORT_FROM post
IMPORT_FROM Session
LOAD_CONST True
STORE_NAME requests_available
POP_TOP None
JUMP_FORWARD 10
JUMP_FORWARD 8
IMPORT_NAME keyring
IMPORT_FROM keyring
IMPORT_FROM get_password
IMPORT_FROM set_password
JUMP_FORWARD 6
JUMP_FORWARD 4
IMPORT_NAME sqlite3
IMPORT_FROM sqlite3
IMPORT_FROM connect
IMPORT_FROM Row
JUMP_FORWARD 6
JUMP_FORWARD 4
IMPORT_NAME winreg
IMPORT_FROM winreg
IMPORT_FROM OpenKey
IMPORT_FROM QueryValueEx
IMPORT_FROM HKEY_LOCAL_MACHINE
JUMP_FORWARD 7
JUMP_FORWARD 5
MAKE_FUNCTION dynamic_import_test_ref_0
STORE_NAME dynamic_import_test
PUSH_NULL None
LOAD_NAME print
LOAD_CONST "--- Extended Import Test Cases: COMPLETED ---"
CALL_FUNCTION 1
POP_TOP None
PUSH_NULL None
LOAD_NAME print
LOAD_CONST "--- Python Compiler Test Suite: Starting ---"
CALL_FUNCTION 1
POP_TOP None
PUSH_NULL None
LOAD_NAME print
LOAD_CONST "\n--- 1. Basic Syntax and Literals ---"
CALL_FUNCTION 1
POP_TOP None
LOAD_CONST """
This is a
multi-line docstring.
"""
POP_TOP None
LOAD_CONST 123.0
STORE_NAME integer_literal
POP_TOP None
LOAD_CONST 3.14
STORE_NAME float_literal
POP_TOP None
LOAD_CONST 2.0
LOAD_CONST 3.0
BINARY_ADD None
STORE_NAME complex_literal
POP_TOP None
LOAD_CONST 0b1010
STORE_NAME binary_literal
POP_TOP None
LOAD_CONST 0o777
STORE_NAME octal_literal
POP_TOP None
LOAD_CONST 0xABC
STORE_NAME hex_literal
POP_TOP None
PUSH_NULL None
LOAD_NAME print
LOAD_CONST "1.2. Numeric Literals: PASSED"
CALL_FUNCTION 1
POP_TOP None
LOAD_CONST "hello"
STORE_NAME single_quoted_string
POP_TOP None
LOAD_CONST "world"
STORE_NAME double_quoted_string
POP_TOP None
LOAD_CONST """
Hello
World
"""
STORE_NAME multi_line_string
POP_TOP None
LOAD_CONST r"C:\new\path"
STORE_NAME raw_string
POP_TOP None
LOAD_CONST Formatted string with 
LOAD_NAME integer_literal
FORMAT_VALUE None
BUILD_STRING 2
STORE_NAME f_string
POP_TOP None
LOAD_CONST b"this is a byte string"
STORE_NAME byte_string
POP_TOP None
PUSH_NULL None
LOAD_NAME print
LOAD_CONST "1.3. String Literals: PASSED"
CALL_FUNCTION 1
POP_TOP None
LOAD_CONST True
STORE_NAME true_literal
POP_TOP None
LOAD_CONST False
STORE_NAME false_literal
POP_TOP None
LOAD_CONST None
STORE_NAME none_literal
POP_TOP None
PUSH_NULL None
LOAD_NAME print
LOAD_CONST "1.4. Boolean and None Literals: PASSED"
CALL_FUNCTION 1
POP_TOP None
PUSH_NULL None
LOAD_NAME print
LOAD_CONST "\n--- 2. Data Types and Operations ---"
CALL_FUNCTION 1
POP_TOP None
LOAD_CONST 10.0
LOAD_CONST 3.0
UNPACK_SEQUENCE 2
STORE_NAME a
STORE_NAME b
STORE_NAME a, b
POP_TOP None
LOAD_NAME a
LOAD_NAME b
BINARY_ADD None
POP_TOP None
LOAD_NAME a
LOAD_NAME b
BINARY_SUBTRACT None
POP_TOP None
LOAD_NAME a
LOAD_NAME b
BINARY_MULTIPLY None
POP_TOP None
LOAD_NAME a
LOAD_NAME b
BINARY_DIVIDE None
POP_TOP None
LOAD_NAME a
LOAD_NAME b
BINARY_FLOOR_DIVIDE None
POP_TOP None
LOAD_NAME a
LOAD_NAME b
BINARY_MODULO None
POP_TOP None
LOAD_NAME a
LOAD_NAME b
BINARY_POWER None
POP_TOP None
LOAD_CONST 5.0
UNARY_NEGATIVE None
STORE_NAME c
POP_TOP None
LOAD_NAME c
UNARY_POSITIVE None
POP_TOP None
LOAD_NAME c
UNARY_NEGATIVE None
POP_TOP None
PUSH_NULL None
LOAD_NAME abs
LOAD_NAME c
CALL_FUNCTION 1
POP_TOP None
PUSH_NULL None
LOAD_NAME divmod
LOAD_NAME a
LOAD_NAME b
CALL_FUNCTION 2
POP_TOP None
PUSH_NULL None
LOAD_NAME pow
LOAD_NAME a
LOAD_NAME b
CALL_FUNCTION 2
POP_TOP None
PUSH_NULL None
LOAD_NAME round
LOAD_CONST 3.14159
LOAD_CONST 2.0
CALL_FUNCTION 2
POP_TOP None
PUSH_NULL None
LOAD_NAME print
LOAD_CONST "2.1. Numeric Types: PASSED"
CALL_FUNCTION 1
POP_TOP None
LOAD_CONST "hello"
STORE_NAME s1
POP_TOP None
LOAD_CONST "world"
STORE_NAME s2
POP_TOP None
LOAD_NAME s1
LOAD_CONST " "
BINARY_ADD None
LOAD_NAME s2
BINARY_ADD None
POP_TOP None
LOAD_NAME s1
LOAD_CONST 3.0
BINARY_MULTIPLY None
POP_TOP None
LOAD_CONST "e"
LOAD_NAME s1
COMPARE_OP None
POP_TOP None
LOAD_CONST "x"
LOAD_NAME s1
COMPARE_OP None
POP_TOP None
LOAD_NAME s1
LOAD_CONST 1.0
BINARY_SUBSCR None
POP_TOP None
LOAD_NAME s1
LOAD_CONST 1.0
UNARY_NEGATIVE None
BINARY_SUBSCR None
POP_TOP None
LOAD_NAME s1
LOAD_CONST None
LOAD_CONST None
LOAD_CONST None
BINARY_OPERATION None
BINARY_SUBSCR None
POP_TOP None
PUSH_NULL None
LOAD_NAME len
LOAD_NAME s1
CALL_FUNCTION 1
POP_TOP None
PUSH_NULL None
LOAD_CONST "Hello"
LOAD_ATTR lower
CALL_FUNCTION 0
POP_TOP None
PUSH_NULL None
LOAD_CONST "world"
LOAD_ATTR upper
CALL_FUNCTION 0
POP_TOP None
PUSH_NULL None
LOAD_CONST "  spaced  "
LOAD_ATTR strip
CALL_FUNCTION 0
POP_TOP None
PUSH_NULL None
LOAD_CONST "comma,separated"
LOAD_ATTR split
LOAD_CONST ","
CALL_FUNCTION 1
POP_TOP None
PUSH_NULL None
LOAD_NAME print
LOAD_CONST "2.2. String Type: PASSED"
CALL_FUNCTION 1
POP_TOP None
LOAD_CONST 1.0
LOAD_CONST "two"
LOAD_CONST 3.0
BUILD_LIST 3
STORE_NAME my_list
POP_TOP None
PUSH_NULL None
LOAD_NAME len
LOAD_NAME my_list
CALL_FUNCTION 1
POP_TOP None
PUSH_NULL None
LOAD_NAME my_list
LOAD_ATTR append
LOAD_CONST 4.0
CALL_FUNCTION 1
POP_TOP None
PUSH_NULL None
LOAD_NAME my_list
LOAD_ATTR pop
CALL_FUNCTION 0
POP_TOP None
LOAD_CONST "one"
LOAD_NAME my_list
LOAD_CONST 0.0
STORE_SUBSCR None
POP_TOP None
LOAD_CONST 1.0
LOAD_CONST 2.0
LOAD_CONST 3.0
BUILD_LIST 2
LOAD_CONST 4.0
BUILD_LIST 3
STORE_NAME nested_list
POP_TOP None
LOAD_NAME nested_list
LOAD_CONST 1.0
BINARY_SUBSCR None
LOAD_CONST 1.0
BINARY_SUBSCR None
POP_TOP None
BUILD_LIST 0
PUSH_NULL None
LOAD_NAME range
LOAD_CONST 5.0
CALL_FUNCTION 1
GET_ITER None
FOR_ITER 13
STORE_NAME x
LOAD_NAME x
LOAD_NAME x
BINARY_MULTIPLY None
LIST_APPEND 1
JUMP_FORWARD 6
STORE_NAME list_comp
POP_TOP None
PUSH_NULL None
LOAD_NAME print
LOAD_CONST "2.3. List Type: PASSED"
CALL_FUNCTION 1
POP_TOP None
LOAD_CONST 1.0
LOAD_CONST "two"
LOAD_CONST 3.0
BUILD_TUPLE 3
STORE_NAME my_tuple
POP_TOP None
PUSH_NULL None
LOAD_NAME len
LOAD_NAME my_tuple
CALL_FUNCTION 1
POP_TOP None
LOAD_NAME my_tuple
LOAD_CONST 1.0
BINARY_SUBSCR None
POP_TOP None
LOAD_CONST "new"
LOAD_NAME my_tuple
LOAD_CONST 1.0
STORE_SUBSCR None
POP_TOP None
PUSH_NULL None
LOAD_NAME print
LOAD_CONST "2.4. Tuple Immutability: FAILED"
CALL_FUNCTION 1
POP_TOP None
JUMP_FORWARD 12
JUMP_FORWARD 10
LOAD_NAME my_tuple
UNPACK_SEQUENCE 3
STORE_NAME a
STORE_NAME b
STORE_NAME c
STORE_NAME a, b, c
POP_TOP None
PUSH_NULL None
LOAD_NAME print
LOAD_CONST "2.4. Tuple Type: PASSED"
CALL_FUNCTION 1
POP_TOP None
LOAD_CONST "one"
LOAD_CONST 1.0
LOAD_CONST "two"
LOAD_CONST 2.0
BUILD_MAP 2
STORE_NAME my_dict
POP_TOP None
LOAD_NAME my_dict
LOAD_CONST "one"
BINARY_SUBSCR None
POP_TOP None
LOAD_CONST 3.0
LOAD_NAME my_dict
LOAD_CONST "three"
STORE_SUBSCR None
POP_TOP None
LOAD_CONST "three"
LOAD_NAME my_dict
COMPARE_OP None
POP_TOP None
PUSH_NULL None
LOAD_NAME list
PUSH_NULL None
LOAD_NAME my_dict
LOAD_ATTR keys
CALL_FUNCTION 0
CALL_FUNCTION 1
POP_TOP None
PUSH_NULL None
LOAD_NAME list
PUSH_NULL None
LOAD_NAME my_dict
LOAD_ATTR values
CALL_FUNCTION 0
CALL_FUNCTION 1
POP_TOP None
LOAD_NAME my_dict
LOAD_CONST "two"
DELETE_SUBSCR None
LOAD_CONST "two"
LOAD_NAME my_dict
COMPARE_OP None
POP_TOP None
BUILD_MAP 0
PUSH_NULL None
LOAD_NAME range
LOAD_CONST 3.0
CALL_FUNCTION 1
GET_ITER None
FOR_ITER 14
STORE_NAME x
LOAD_NAME x
LOAD_NAME x
LOAD_NAME x
BINARY_MULTIPLY None
MAP_ADD 1
JUMP_FORWARD 6
STORE_NAME dict_comp
POP_TOP None
PUSH_NULL None
LOAD_NAME print
LOAD_CONST "2.5. Dictionary Type: PASSED"
CALL_FUNCTION 1
POP_TOP None
LOAD_CONST 1.0
LOAD_CONST 2.0
LOAD_CONST 2.0
LOAD_CONST 3.0
BUILD_SET 4
STORE_NAME my_set
POP_TOP None
PUSH_NULL None
LOAD_NAME my_set
LOAD_ATTR add
LOAD_CONST 4.0
CALL_FUNCTION 1
POP_TOP None
LOAD_CONST 4.0
LOAD_NAME my_set
COMPARE_OP None
POP_TOP None
PUSH_NULL None
LOAD_NAME my_set
LOAD_ATTR remove
LOAD_CONST 2.0
CALL_FUNCTION 1
POP_TOP None
LOAD_CONST 2.0
LOAD_NAME my_set
COMPARE_OP None
POP_TOP None
LOAD_CONST 1.0
LOAD_CONST 2.0
LOAD_CONST 3.0
BUILD_SET 3
STORE_NAME set1
POP_TOP None
LOAD_CONST 3.0
LOAD_CONST 4.0
LOAD_CONST 5.0
BUILD_SET 3
STORE_NAME set2
POP_TOP None
LOAD_NAME set1
LOAD_NAME set2
BINARY_OR None
POP_TOP None
LOAD_NAME set1
LOAD_NAME set2
BINARY_AND None
POP_TOP None
LOAD_NAME set1
LOAD_NAME set2
BINARY_SUBTRACT None
POP_TOP None
LOAD_NAME set1
LOAD_NAME set2
BINARY_XOR None
POP_TOP None
BUILD_SET 0
LOAD_CONST "abracadabra"
GET_ITER None
FOR_ITER 12
STORE_NAME x
LOAD_NAME x
LOAD_CONST "abc"
COMPARE_OP None
POP_JUMP_IF_FALSE 3
LOAD_NAME x
SET_ADD 1
JUMP_FORWARD 3
STORE_NAME set_comp
POP_TOP None
PUSH_NULL None
LOAD_NAME print
LOAD_CONST "2.6. Set Type: PASSED"
CALL_FUNCTION 1
POP_TOP None
PUSH_NULL None
LOAD_NAME print
LOAD_CONST "\n--- 3. Control Flow ---"
CALL_FUNCTION 1
POP_TOP None
LOAD_CONST 10.0
STORE_NAME x
POP_TOP None
LOAD_NAME x
LOAD_CONST 5.0
COMPARE_OP None
POP_JUMP_IF_FALSE 8
LOAD_CONST "greater"
STORE_NAME result
POP_TOP None
JUMP_FORWARD 14
LOAD_NAME x
LOAD_CONST 5.0
COMPARE_OP None
LOAD_CONST "equal"
STORE_NAME result
POP_TOP None
PUSH_NULL None
LOAD_NAME print
LOAD_CONST "3.1. if/elif/else: PASSED"
CALL_FUNCTION 1
POP_TOP None
LOAD_CONST 0.0
STORE_NAME total
POP_TOP None
PUSH_NULL None
LOAD_NAME range
LOAD_CONST 5.0
CALL_FUNCTION 1
LOAD_NAME total
LOAD_NAME i
BINARY_OPERATION None
STORE_NAME total
POP_TOP None
LOAD_CONST 1.0
LOAD_CONST 2.0
LOAD_CONST 3.0
BUILD_LIST 3
LOAD_NAME i
LOAD_CONST 4.0
COMPARE_OP None
POP_JUMP_IF_FALSE 5
BINARY_OPERATION None
LOAD_CONST 5.0
STORE_NAME count
POP_TOP None
LOAD_NAME count
LOAD_CONST 0.0
COMPARE_OP None
POP_JUMP_IF_FALSE 5
LOAD_NAME count
LOAD_CONST 1.0
BINARY_OPERATION None
STORE_NAME count
POP_TOP None
LOAD_CONST 3.0
STORE_NAME count
POP_TOP None
LOAD_NAME count
LOAD_CONST 0.0
COMPARE_OP None
POP_JUMP_IF_FALSE 5
LOAD_NAME count
LOAD_CONST 1.0
BINARY_OPERATION None
STORE_NAME count
POP_TOP None
LOAD_NAME count
LOAD_CONST 1.0
UNARY_NEGATIVE None
COMPARE_OP None
POP_JUMP_IF_FALSE 6
BINARY_OPERATION None
LOAD_CONST False
STORE_NAME found_even
POP_TOP None
PUSH_NULL None
LOAD_NAME range
LOAD_CONST 10.0
CALL_FUNCTION 1
LOAD_NAME i
LOAD_CONST 2.0
BINARY_MODULO None
LOAD_CONST 0.0
COMPARE_OP None
POP_JUMP_IF_FALSE 7
BINARY_OPERATION None
LOAD_NAME i
LOAD_CONST 5.0
COMPARE_OP None
POP_JUMP_IF_FALSE 5
BINARY_OPERATION None
LOAD_NAME i
LOAD_CONST 4.0
COMPARE_OP None
POP_JUMP_IF_FALSE 7
LOAD_CONST True
STORE_NAME found_even
POP_TOP None
PUSH_NULL None
LOAD_NAME print
LOAD_CONST "3.6. break and continue: PASSED"
CALL_FUNCTION 1
POP_TOP None
LOAD_CONST 1.0
LOAD_CONST 0.0
BINARY_DIVIDE None
POP_TOP None
JUMP_FORWARD 6
JUMP_FORWARD 4
MAKE_CLASS MyContext_ref_3
STORE_NAME MyContext
LOAD_NAME cm
ENTER_CONTEXT None
COPY 3
EXIT_CONTEXT None
PUSH_NULL None
LOAD_NAME print
LOAD_CONST "3.8. with statement: PASSED"
CALL_FUNCTION 1
POP_TOP None
PUSH_NULL None
LOAD_NAME print
LOAD_CONST "\n--- 4. Functions and Scopes ---"
CALL_FUNCTION 1
POP_TOP None
MAKE_FUNCTION greet_ref_4
STORE_NAME greet
PUSH_NULL None
LOAD_NAME greet
LOAD_CONST "World"
CALL_FUNCTION 1
POP_TOP None
MAKE_FUNCTION func_with_args_ref_5
STORE_NAME func_with_args
PUSH_NULL None
LOAD_NAME func_with_args
LOAD_CONST 1.0
LOAD_CONST 2.0
CALL_FUNCTION 2
POP_TOP None
PUSH_NULL None
LOAD_NAME func_with_args
LOAD_CONST 1.0
LOAD_CONST 2.0
LOAD_CONST 3.0
CALL_FUNCTION 3
POP_TOP None
PUSH_NULL None
LOAD_NAME func_with_args
LOAD_CONST a
LOAD_CONST 5.0
LOAD_CONST b
LOAD_CONST 5.0
KW_NAMES kwnames_2
CALL_FUNCTION 2
POP_TOP None
PUSH_NULL None
LOAD_NAME func_with_args
LOAD_CONST c
LOAD_CONST 1.0
LOAD_CONST b
LOAD_CONST 2.0
LOAD_CONST a
LOAD_CONST 3.0
KW_NAMES kwnames_3
CALL_FUNCTION 3
POP_TOP None
MAKE_FUNCTION func_with_arbitrary_args_ref_6
STORE_NAME func_with_arbitrary_args
PUSH_NULL None
LOAD_NAME func_with_arbitrary_args
LOAD_CONST 1.0
LOAD_CONST 2.0
LOAD_CONST name
LOAD_CONST "test"
LOAD_CONST value
LOAD_CONST 123.0
KW_NAMES kwnames_2
CALL_FUNCTION 4
UNPACK_SEQUENCE 2
STORE_NAME args_val
STORE_NAME kwargs_val
STORE_NAME args_val, kwargs_val
POP_TOP None
MAKE_FUNCTION lambda_ref_7
STORE_NAME multiply
POP_TOP None
PUSH_NULL None
LOAD_NAME multiply
LOAD_CONST 3.0
LOAD_CONST 4.0
CALL_FUNCTION 2
POP_TOP None
MAKE_FUNCTION outer_func_ref_9
STORE_NAME outer_func
PUSH_NULL None
LOAD_NAME outer_func
CALL_FUNCTION 0
STORE_NAME closure
POP_TOP None
PUSH_NULL None
LOAD_NAME closure
CALL_FUNCTION 0
POP_TOP None
PUSH_NULL None
LOAD_NAME closure
CALL_FUNCTION 0
POP_TOP None
LOAD_CONST 100.0
STORE_GLOBAL global_var
POP_TOP None
MAKE_FUNCTION modify_global_ref_10
STORE_NAME modify_global
PUSH_NULL None
LOAD_NAME modify_global
CALL_FUNCTION 0
POP_TOP None
PUSH_NULL None
LOAD_NAME print
LOAD_CONST "4.1-4.6. Functions and Scopes: PASSED"
CALL_FUNCTION 1
POP_TOP None
PUSH_NULL None
LOAD_NAME print
LOAD_CONST "\n--- 5. Object-Oriented Programming ---"
CALL_FUNCTION 1
POP_TOP None
MAKE_CLASS MyClass_ref_15
STORE_NAME MyClass
PUSH_NULL None
LOAD_NAME MyClass
LOAD_CONST 20.0
CALL_FUNCTION 1
STORE_NAME obj
POP_TOP None
LOAD_NAME obj
LOAD_ATTR instance_variable
POP_TOP None
PUSH_NULL None
LOAD_NAME obj
LOAD_ATTR instance_method
CALL_FUNCTION 0
POP_TOP None
LOAD_NAME MyClass
LOAD_ATTR class_variable
POP_TOP None
PUSH_NULL None
LOAD_NAME MyClass
LOAD_ATTR class_method
CALL_FUNCTION 0
POP_TOP None
PUSH_NULL None
LOAD_NAME MyClass
LOAD_ATTR static_method
CALL_FUNCTION 0
POP_TOP None
PUSH_NULL None
LOAD_NAME print
LOAD_CONST "5.1. Classes: PASSED"
CALL_FUNCTION 1
POP_TOP None
MAKE_CLASS ParentA_ref_17
STORE_NAME ParentA
MAKE_CLASS ParentB_ref_19
STORE_NAME ParentB
MAKE_CLASS Child_ref_21
STORE_NAME Child
PUSH_NULL None
LOAD_NAME Child
CALL_FUNCTION 0
STORE_NAME child_obj
POP_TOP None
PUSH_NULL None
LOAD_NAME child_obj
LOAD_ATTR method_a
CALL_FUNCTION 0
POP_TOP None
PUSH_NULL None
LOAD_NAME child_obj
LOAD_ATTR method_b
CALL_FUNCTION 0
POP_TOP None
PUSH_NULL None
LOAD_NAME child_obj
LOAD_ATTR method_c
CALL_FUNCTION 0
POP_TOP None
PUSH_NULL None
LOAD_NAME print
LOAD_CONST "5.2. Inheritance: PASSED"
CALL_FUNCTION 1
POP_TOP None
MAKE_CLASS Vector_ref_27
STORE_NAME Vector
PUSH_NULL None
LOAD_NAME Vector
LOAD_CONST 1.0
LOAD_CONST 2.0
CALL_FUNCTION 2
STORE_NAME v1
POP_TOP None
PUSH_NULL None
LOAD_NAME Vector
LOAD_CONST 3.0
LOAD_CONST 4.0
CALL_FUNCTION 2
STORE_NAME v2
POP_TOP None
LOAD_NAME v1
LOAD_NAME v2
BINARY_ADD None
STORE_NAME v3
POP_TOP None
PUSH_NULL None
LOAD_NAME repr
LOAD_NAME v3
CALL_FUNCTION 1
POP_TOP None
PUSH_NULL None
LOAD_NAME len
LOAD_NAME v3
CALL_FUNCTION 1
POP_TOP None
LOAD_NAME v3
LOAD_CONST 0.0
BINARY_SUBSCR None
POP_TOP None
PUSH_NULL None
LOAD_NAME print
LOAD_CONST "5.3. Dunder Methods: PASSED"
CALL_FUNCTION 1
POP_TOP None
MAKE_CLASS Circle_ref_32
STORE_NAME Circle
PUSH_NULL None
LOAD_NAME Circle
LOAD_CONST 5.0
CALL_FUNCTION 1
STORE_NAME c
POP_TOP None
LOAD_NAME c
LOAD_ATTR radius
POP_TOP None
LOAD_NAME c
LOAD_ATTR area
POP_TOP None
LOAD_CONST 10.0
LOAD_NAME c
STORE_ATTR radius
POP_TOP None
LOAD_NAME c
LOAD_ATTR radius
POP_TOP None
LOAD_CONST 1.0
UNARY_NEGATIVE None
LOAD_NAME c
STORE_ATTR radius
POP_TOP None
JUMP_FORWARD 7
JUMP_FORWARD 5
PUSH_NULL None
LOAD_NAME print
LOAD_CONST "\n--- 6. Advanced Features ---"
CALL_FUNCTION 1
POP_TOP None
MAKE_FUNCTION my_decorator_ref_34
STORE_NAME my_decorator
MAKE_FUNCTION say_whee_ref_35
STORE_NAME say_whee
PUSH_NULL None
LOAD_NAME say_whee
CALL_FUNCTION 0
POP_TOP None
PUSH_NULL None
LOAD_NAME print
LOAD_CONST "6.1. Decorators: PASSED"
CALL_FUNCTION 1
POP_TOP None
GENERATOR_FUNCTION my_generator_ref_36
STORE_NAME my_generator
PUSH_NULL None
LOAD_NAME my_generator
LOAD_CONST 3.0
CALL_FUNCTION 1
STORE_NAME gen
POP_TOP None
PUSH_NULL None
LOAD_NAME next
LOAD_NAME gen
CALL_FUNCTION 1
POP_TOP None
PUSH_NULL None
LOAD_NAME next
LOAD_NAME gen
CALL_FUNCTION 1
POP_TOP None
PUSH_NULL None
LOAD_NAME next
LOAD_NAME gen
CALL_FUNCTION 1
POP_TOP None
PUSH_NULL None
LOAD_NAME next
LOAD_NAME gen
CALL_FUNCTION 1
POP_TOP None
JUMP_FORWARD 7
JUMP_FORWARD 5
ASYNC_FUNCTION my_coroutine_ref_37
STORE_NAME my_coroutine
ASYNC_FUNCTION main_async_ref_38
STORE_NAME main_async
PUSH_NULL None
LOAD_NAME asyncio
LOAD_ATTR run
PUSH_NULL None
LOAD_NAME main_async
CALL_FUNCTION 0
CALL_FUNCTION 1
POP_TOP None
MAKE_CLASS MyMeta_ref_40
STORE_NAME MyMeta
MAKE_CLASS MyClassWithMeta_ref_41
STORE_NAME MyClassWithMeta
PUSH_NULL None
LOAD_NAME hasattr
LOAD_NAME MyClassWithMeta
LOAD_CONST "new_attribute"
CALL_FUNCTION 2
POP_TOP None
LOAD_NAME MyClassWithMeta
LOAD_ATTR new_attribute
POP_TOP None
PUSH_NULL None
LOAD_NAME print
LOAD_CONST "6.4. Metaclasses: PASSED"
CALL_FUNCTION 1
POP_TOP None
MAKE_FUNCTION hinted_function_ref_42
STORE_NAME hinted_function
PUSH_NULL None
LOAD_NAME hinted_function
LOAD_CONST "Alice"
LOAD_CONST 30.0
CALL_FUNCTION 2
POP_TOP None
PUSH_NULL None
LOAD_NAME print
LOAD_CONST "6.5. Type Hinting: PASSED"
CALL_FUNCTION 1
POP_TOP None
PUSH_NULL None
LOAD_NAME print
LOAD_CONST "\n--- 7. Standard Library Usage ---"
CALL_FUNCTION 1
POP_TOP None
PUSH_NULL None
LOAD_NAME math
LOAD_ATTR sqrt
LOAD_CONST 16.0
CALL_FUNCTION 1
POP_TOP None
PUSH_NULL None
LOAD_NAME math
LOAD_ATTR isclose
LOAD_NAME math
LOAD_ATTR pi
LOAD_CONST 3.14159
LOAD_CONST rel_tol
LOAD_CONST 1e-05
KW_NAMES kwnames_1
CALL_FUNCTION 3
POP_TOP None
PUSH_NULL None
LOAD_NAME cmath
LOAD_ATTR sqrt
LOAD_CONST 1.0
UNARY_NEGATIVE None
CALL_FUNCTION 1
POP_TOP None
PUSH_NULL None
LOAD_NAME print
LOAD_CONST "7.1. math and cmath: PASSED"
CALL_FUNCTION 1
POP_TOP None
PUSH_NULL None
LOAD_NAME collections
LOAD_ATTR deque
LOAD_CONST 1.0
LOAD_CONST 2.0
LOAD_CONST 3.0
BUILD_LIST 3
CALL_FUNCTION 1
STORE_NAME d
POP_TOP None
PUSH_NULL None
LOAD_NAME d
LOAD_ATTR appendleft
LOAD_CONST 0.0
CALL_FUNCTION 1
POP_TOP None
PUSH_NULL None
LOAD_NAME collections
LOAD_ATTR namedtuple
LOAD_CONST "Point"
LOAD_CONST "x"
LOAD_CONST "y"
BUILD_LIST 2
CALL_FUNCTION 2
STORE_NAME Point
POP_TOP None
PUSH_NULL None
LOAD_NAME Point
LOAD_CONST 1.0
LOAD_CONST 2.0
CALL_FUNCTION 2
STORE_NAME p
POP_TOP None
LOAD_NAME p
LOAD_ATTR x
POP_TOP None
LOAD_NAME p
LOAD_ATTR y
POP_TOP None
PUSH_NULL None
LOAD_NAME print
LOAD_CONST "7.2. collections: PASSED"
CALL_FUNCTION 1
POP_TOP None
PUSH_NULL None
LOAD_NAME itertools
LOAD_ATTR count
LOAD_CONST start
LOAD_CONST 5.0
LOAD_CONST step
LOAD_CONST 2.0
KW_NAMES kwnames_2
CALL_FUNCTION 2
STORE_NAME counter
POP_TOP None
PUSH_NULL None
LOAD_NAME next
LOAD_NAME counter
CALL_FUNCTION 1
POP_TOP None
PUSH_NULL None
LOAD_NAME next
LOAD_NAME counter
CALL_FUNCTION 1
POP_TOP None
PUSH_NULL None
LOAD_NAME list
PUSH_NULL None
LOAD_NAME itertools
LOAD_ATTR permutations
LOAD_CONST "AB"
CALL_FUNCTION 1
CALL_FUNCTION 1
STORE_NAME permutations
POP_TOP None
PUSH_NULL None
LOAD_NAME print
LOAD_CONST "7.3. itertools: PASSED"
CALL_FUNCTION 1
POP_TOP None
LOAD_CONST '{"name": "John", "age": 30}'
STORE_NAME json_string
POP_TOP None
PUSH_NULL None
LOAD_NAME json
LOAD_ATTR loads
LOAD_NAME json_string
CALL_FUNCTION 1
STORE_NAME data
POP_TOP None
LOAD_NAME data
LOAD_CONST "name"
BINARY_SUBSCR None
POP_TOP None
PUSH_NULL None
LOAD_NAME json
LOAD_ATTR dumps
LOAD_NAME data
CALL_FUNCTION 1
STORE_NAME new_json_string
POP_TOP None
PUSH_NULL None
LOAD_NAME json
LOAD_ATTR loads
LOAD_NAME new_json_string
CALL_FUNCTION 1
POP_TOP None
PUSH_NULL None
LOAD_NAME print
LOAD_CONST "7.4. json: PASSED"
CALL_FUNCTION 1
POP_TOP None
LOAD_CONST "The rain in Spain"
STORE_NAME text
POP_TOP None
PUSH_NULL None
LOAD_NAME re
LOAD_ATTR search
LOAD_CONST r"^The.*Spain$"
LOAD_NAME text
CALL_FUNCTION 2
STORE_NAME match
POP_TOP None
PUSH_NULL None
LOAD_NAME re
LOAD_ATTR findall
LOAD_CONST r"ai"
LOAD_NAME text
CALL_FUNCTION 2
STORE_NAME found
POP_TOP None
PUSH_NULL None
LOAD_NAME print
LOAD_CONST "7.5. re: PASSED"
CALL_FUNCTION 1
POP_TOP None
PUSH_NULL None
LOAD_NAME print
LOAD_CONST "\n--- 8. Dynamic Features and Introspection ---"
CALL_FUNCTION 1
POP_TOP None
MAKE_CLASS DynamicClass_ref_43
STORE_NAME DynamicClass
PUSH_NULL None
LOAD_NAME DynamicClass
CALL_FUNCTION 0
STORE_NAME dyn_obj
POP_TOP None
PUSH_NULL None
LOAD_NAME setattr
LOAD_NAME dyn_obj
LOAD_CONST "dynamic_attr"
LOAD_CONST 123.0
CALL_FUNCTION 3
POP_TOP None
PUSH_NULL None
LOAD_NAME hasattr
LOAD_NAME dyn_obj
LOAD_CONST "dynamic_attr"
CALL_FUNCTION 2
POP_TOP None
PUSH_NULL None
LOAD_NAME getattr
LOAD_NAME dyn_obj
LOAD_CONST "dynamic_attr"
CALL_FUNCTION 2
POP_TOP None
PUSH_NULL None
LOAD_NAME delattr
LOAD_NAME dyn_obj
LOAD_CONST "dynamic_attr"
CALL_FUNCTION 2
POP_TOP None
PUSH_NULL None
LOAD_NAME hasattr
LOAD_NAME dyn_obj
LOAD_CONST "dynamic_attr"
CALL_FUNCTION 2
LOGICAL_NOT None
POP_TOP None
PUSH_NULL None
LOAD_NAME print
LOAD_CONST "8.1. Dynamic attribute access: PASSED"
CALL_FUNCTION 1
POP_TOP None
PUSH_NULL None
LOAD_NAME eval
LOAD_CONST "2 + 3 * 4"
CALL_FUNCTION 1
STORE_NAME eval_result
POP_TOP None
LOAD_CONST "dynamic_var = 10"
STORE_NAME exec_code
POP_TOP None
PUSH_NULL None
LOAD_NAME exec
LOAD_NAME exec_code
CALL_FUNCTION 1
POP_TOP None
PUSH_NULL None
LOAD_NAME print
LOAD_CONST "8.2. eval() and exec(): PASSED (if no exceptions were raised)"
CALL_FUNCTION 1
POP_TOP None
PUSH_NULL None
LOAD_NAME isinstance
LOAD_CONST 1.0
LOAD_NAME int
CALL_FUNCTION 2
POP_TOP None
PUSH_NULL None
LOAD_NAME isinstance
LOAD_CONST "hello"
LOAD_NAME int
CALL_FUNCTION 2
LOGICAL_NOT None
POP_TOP None
PUSH_NULL None
LOAD_NAME issubclass
LOAD_NAME bool
LOAD_NAME int
CALL_FUNCTION 2
POP_TOP None
PUSH_NULL None
LOAD_GLOBAL type
LOAD_CONST 123.0
CALL_FUNCTION 1
LOAD_NAME int
COMPARE_OP None
POP_TOP None
PUSH_NULL None
LOAD_NAME print
LOAD_CONST "8.3. Type introspection: PASSED"
CALL_FUNCTION 1
POP_TOP None
PUSH_NULL None
LOAD_NAME print
LOAD_CONST "\n--- 9. Missing Node Types Coverage ---"
CALL_FUNCTION 1
POP_TOP None
LOAD_CONST True
STORE_NAME bool_true
POP_TOP None
LOAD_CONST False
STORE_NAME bool_false
POP_TOP None
LOAD_CONST None
STORE_NAME none_val
POP_TOP None
LOAD_CONST ...
STORE_NAME ellipsis_val
POP_TOP None
MAKE_FUNCTION function_with_ellipsis_ref_44
STORE_NAME function_with_ellipsis
LOAD_CONST 42.0
UNARY_NEGATIVE None
STORE_NAME negative_num
POP_TOP None
LOAD_CONST 42.0
UNARY_POSITIVE None
STORE_NAME positive_num
POP_TOP None
LOAD_CONST 42.0
UNARY_INVERT None
STORE_NAME bitwise_not
POP_TOP None
LOAD_CONST True
LOGICAL_NOT None
STORE_NAME logical_not
POP_TOP None
LOAD_CONST 10.0
STORE_NAME aug_val
POP_TOP None
LOAD_NAME aug_val
LOAD_CONST 5.0
BINARY_OPERATION None
STORE_NAME aug_val
POP_TOP None
LOAD_NAME aug_val
LOAD_CONST 2.0
BINARY_OPERATION None
STORE_NAME aug_val
POP_TOP None
LOAD_NAME aug_val
LOAD_CONST 3.0
BINARY_OPERATION None
STORE_NAME aug_val
POP_TOP None
LOAD_NAME aug_val
LOAD_CONST 2.0
BINARY_OPERATION None
STORE_NAME aug_val
POP_TOP None
LOAD_CONST 1.0
LOAD_CONST 2.0
COMPARE_OP None
LOAD_CONST 2.0
LOAD_CONST 1.0
COMPARE_OP None
LOGICAL_AND None
LOAD_CONST 3.0
LOAD_CONST 3.0
COMPARE_OP None
LOGICAL_OR None
STORE_NAME comp_result
POP_TOP None
LOAD_NAME bool_true
LOAD_CONST True
COMPARE_OP None
STORE_NAME is_result
POP_TOP None
LOAD_CONST "a"
LOAD_CONST "abc"
COMPARE_OP None
STORE_NAME in_result
POP_TOP None
LOAD_CONST "z"
LOAD_CONST "abc"
COMPARE_OP None
STORE_NAME not_in_result
POP_TOP None
MAKE_FUNCTION lambda_ref_45
STORE_NAME lambda_func
POP_TOP None
PUSH_NULL None
LOAD_NAME lambda_func
LOAD_CONST 5.0
CALL_FUNCTION 1
STORE_NAME lambda_result
POP_TOP None
POP_JUMP_IF_FALSE 2
JUMP_FORWARD 2
STORE_NAME ternary_result
POP_TOP None
BUILD_LIST 0
PUSH_NULL None
LOAD_NAME range
LOAD_CONST 3.0
CALL_FUNCTION 1
GET_ITER None
FOR_ITER 13
STORE_NAME x
LOAD_NAME x
LOAD_CONST 2.0
BINARY_MULTIPLY None
LIST_APPEND 1
JUMP_FORWARD 6
STORE_NAME list_comp
POP_TOP None
BUILD_MAP 0
PUSH_NULL None
LOAD_NAME range
LOAD_CONST 3.0
CALL_FUNCTION 1
GET_ITER None
FOR_ITER 14
STORE_NAME x
LOAD_NAME x
LOAD_NAME x
LOAD_CONST 2.0
BINARY_MULTIPLY None
MAP_ADD 1
JUMP_FORWARD 6
STORE_NAME dict_comp
POP_TOP None
BUILD_SET 0
PUSH_NULL None
LOAD_NAME range
LOAD_CONST 3.0
CALL_FUNCTION 1
GET_ITER None
FOR_ITER 13
STORE_NAME x
LOAD_NAME x
LOAD_CONST 2.0
BINARY_MULTIPLY None
SET_ADD 1
JUMP_FORWARD 6
STORE_NAME set_comp
POP_TOP None
PUSH_NULL None
LOAD_NAME range
LOAD_CONST 3.0
CALL_FUNCTION 1
GET_ITER None
FOR_ITER 11
STORE_NAME x
LOAD_NAME x
LOAD_CONST 2.0
BINARY_MULTIPLY None
JUMP_FORWARD 5
STORE_NAME gen_expr
POP_TOP None
LOAD_CONST 1.0
LOAD_CONST 0.0
BINARY_DIVIDE None
STORE_NAME risky_operation
POP_TOP None
JUMP_FORWARD 8
JUMP_FORWARD 5
JUMP_FORWARD 5
PUSH_NULL None
LOAD_NAME range
LOAD_CONST 2.0
CALL_FUNCTION 1
LOAD_NAME i
LOAD_CONST 10.0
COMPARE_OP None
POP_JUMP_IF_FALSE 5
BINARY_OPERATION None
LOAD_CONST 0.0
STORE_NAME count
POP_TOP None
LOAD_NAME count
LOAD_CONST 2.0
COMPARE_OP None
POP_JUMP_IF_FALSE 5
LOAD_NAME count
LOAD_CONST 1.0
BINARY_OPERATION None
STORE_NAME count
POP_TOP None
MAKE_CLASS SimpleContext_ref_48
STORE_NAME SimpleContext
LOAD_NAME ctx_val
ENTER_CONTEXT None
LOAD_NAME ctx_val
STORE_NAME context_result
POP_TOP None
COPY 3
EXIT_CONTEXT None
LOAD_NAME ctx1
ENTER_CONTEXT None
LOAD_NAME ctx2
ENTER_CONTEXT None
LOAD_NAME ctx1
LOAD_NAME ctx2
BINARY_ADD None
STORE_NAME multi_context_result
POP_TOP None
COPY 3
EXIT_CONTEXT None
COPY 3
EXIT_CONTEXT None
LOAD_CONST 1.0
LOAD_CONST 1.0
COMPARE_OP None
BINARY_OPERATION None
MAKE_FUNCTION empty_func_ref_49
STORE_NAME empty_func
PUSH_NULL None
LOAD_NAME range
LOAD_CONST 5.0
CALL_FUNCTION 1
LOAD_NAME i
LOAD_CONST 1.0
COMPARE_OP None
POP_JUMP_IF_FALSE 5
BINARY_OPERATION None
LOAD_NAME i
LOAD_CONST 3.0
COMPARE_OP None
POP_JUMP_IF_FALSE 5
BINARY_OPERATION None
MAKE_FUNCTION test_raise_ref_50
STORE_NAME test_raise
IMPORT_FROM math
IMPORT_FROM sqrt
IMPORT_FROM square_root
IMPORT_NAME sys
IMPORT_NAME system
LOAD_CONST "global"
STORE_GLOBAL global_var
POP_TOP None
MAKE_FUNCTION test_global_ref_51
STORE_NAME test_global
MAKE_FUNCTION outer_ref_53
STORE_NAME outer
LOAD_CONST 42.0
STORE_GLOBAL simple_global
POP_TOP None
MAKE_FUNCTION read_simple_global_ref_54
STORE_NAME read_simple_global
MAKE_FUNCTION modify_simple_global_ref_55
STORE_NAME modify_simple_global
LOAD_CONST 10.0
STORE_GLOBAL global_x
POP_TOP None
LOAD_CONST 20.0
STORE_GLOBAL global_y
POP_TOP None
LOAD_CONST 30.0
STORE_GLOBAL global_z
POP_TOP None
MAKE_FUNCTION multiple_globals_ref_56
STORE_NAME multiple_globals
LOAD_CONST "I am global"
STORE_GLOBAL mixed_var
POP_TOP None
MAKE_FUNCTION mixed_scope_ref_57
STORE_NAME mixed_scope
LOAD_CONST "key"
LOAD_CONST "value"
BUILD_MAP 1
STORE_GLOBAL context_global
POP_TOP None
MAKE_FUNCTION global_in_expressions_ref_58
STORE_NAME global_in_expressions
MAKE_FUNCTION global_function_ref_59
STORE_NAME global_function
MAKE_CLASS GlobalClass_ref_60
STORE_NAME GlobalClass
MAKE_FUNCTION test_global_callables_ref_61
STORE_NAME test_global_callables
LOAD_CONST "outer"
STORE_GLOBAL outer_global
POP_TOP None
MAKE_FUNCTION outer_with_global_ref_63
STORE_NAME outer_with_global
LOAD_CONST 1.0
LOAD_CONST 2.0
LOAD_CONST 3.0
LOAD_CONST 4.0
LOAD_CONST 5.0
BUILD_LIST 5
STORE_GLOBAL comp_global
POP_TOP None
MAKE_FUNCTION global_in_comprehensions_ref_64
STORE_NAME global_in_comprehensions
LOAD_CONST "global shadow"
STORE_GLOBAL shadow_var
POP_TOP None
MAKE_FUNCTION shadow_test_ref_67
STORE_NAME shadow_test
LOAD_CONST "my custom type"
STORE_GLOBAL type
POP_TOP None
MAKE_FUNCTION global_shadowing_builtin_ref_68
STORE_NAME global_shadowing_builtin
LOAD_CONST 42.0
STORE_NAME temp_var
POP_TOP None
DELETE_NAME temp_var
LOAD_CONST 0xFF
LOAD_CONST 0x0F
BINARY_AND None
STORE_NAME bitwise_and
POP_TOP None
LOAD_CONST 0x10
LOAD_CONST 0x01
BINARY_OR None
STORE_NAME bitwise_or
POP_TOP None
LOAD_CONST 0xAA
LOAD_CONST 0x55
BINARY_XOR None
STORE_NAME bitwise_xor
POP_TOP None
LOAD_CONST 8.0
LOAD_CONST 2.0
BINARY_LSHIFT None
STORE_NAME left_shift
POP_TOP None
LOAD_CONST 32.0
LOAD_CONST 3.0
BINARY_RSHIFT None
STORE_NAME right_shift
POP_TOP None
LOAD_CONST 17.0
LOAD_CONST 5.0
BINARY_FLOOR_DIVIDE None
STORE_NAME floor_div
POP_TOP None
LOAD_CONST 5.0
LOAD_CONST 50.0
UNPACK_SEQUENCE 2
STORE_NAME x
STORE_NAME y
STORE_NAME x, y
POP_TOP None
LOAD_CONST 1.0
LOAD_NAME x
COPY 1
LOAD_CONST 10.0
COMPARE_OP None
LOAD_CONST 0.0
LOAD_NAME y
COPY 1
LOAD_CONST 100.0
COMPARE_OP None
LOGICAL_AND None
STORE_NAME chained_comp
POP_TOP None
LOAD_CONST 0.0
LOAD_NAME x
COPY 1
LOAD_CONST 10.0
COMPARE_OP None
STORE_NAME is_between
POP_TOP None
LOAD_NAME x
LOAD_CONST 5.0
COMPARE_OP None
STORE_NAME greater_equal
POP_TOP None
LOAD_NAME y
LOAD_CONST 100.0
COMPARE_OP None
STORE_NAME less_equal
POP_TOP None
LOAD_NAME x
LOAD_NAME y
COMPARE_OP None
STORE_NAME not_equal
POP_TOP None
PUSH_NULL None
LOAD_NAME len
LOAD_CONST "test"
CALL_FUNCTION 1
STORE_NAME n
LOAD_NAME n
LOAD_CONST 3.0
COMPARE_OP None
POP_JUMP_IF_FALSE 12
LOAD_NAME n
STORE_NAME walrus_result
POP_TOP None
PUSH_NULL None
LOAD_NAME print
LOAD_CONST "9. Missing Node Types Coverage: PASSED"
CALL_FUNCTION 1
POP_TOP None
LOAD_CONST 1.0
LOAD_CONST 2.0
LOAD_CONST 3.0
LOAD_CONST 4.0
LOAD_CONST 5.0
BUILD_LIST 5
STORE_NAME test_list
POP_TOP None
LOAD_NAME test_list
LOAD_CONST 0.0
BINARY_SUBSCR None
STORE_NAME first_element
POP_TOP None
LOAD_NAME test_list
LOAD_CONST 1.0
UNARY_NEGATIVE None
BINARY_SUBSCR None
STORE_NAME last_element
POP_TOP None
LOAD_NAME test_list
LOAD_CONST None
LOAD_CONST None
LOAD_CONST None
BINARY_OPERATION None
BINARY_SUBSCR None
STORE_NAME slice_access
POP_TOP None
LOAD_NAME test_list
LOAD_CONST None
LOAD_CONST None
LOAD_CONST None
BINARY_OPERATION None
BINARY_SUBSCR None
STORE_NAME step_slice
POP_TOP None
LOAD_CONST "api_key"
LOAD_CONST "secret123"
LOAD_CONST "endpoint"
LOAD_CONST "https://malicious.com/api"
LOAD_CONST "payload"
LOAD_CONST "data"
LOAD_CONST "encoded"
BUILD_MAP 1
BUILD_MAP 3
STORE_NAME config_dict
POP_TOP None
LOAD_NAME config_dict
LOAD_CONST "api_key"
BINARY_SUBSCR None
STORE_NAME api_key
POP_TOP None
LOAD_NAME config_dict
LOAD_CONST "endpoint"
BINARY_SUBSCR None
STORE_NAME endpoint
POP_TOP None
LOAD_NAME config_dict
LOAD_CONST "pay"
LOAD_CONST "load"
BINARY_ADD None
BINARY_SUBSCR None
STORE_NAME dynamic_key
POP_TOP None
LOAD_CONST "users"
LOAD_CONST "name"
LOAD_CONST "admin"
LOAD_CONST "permissions"
LOAD_CONST "read"
LOAD_CONST "write"
LOAD_CONST "execute"
BUILD_LIST 3
BUILD_MAP 2
LOAD_CONST "name"
LOAD_CONST "guest"
LOAD_CONST "permissions"
LOAD_CONST "read"
BUILD_LIST 1
BUILD_MAP 2
BUILD_LIST 2
LOAD_CONST "config"
LOAD_CONST "servers"
LOAD_CONST "192.168.1.1"
LOAD_CONST "10.0.0.1"
BUILD_LIST 2
LOAD_CONST "ports"
LOAD_CONST 80.0
LOAD_CONST 443.0
LOAD_CONST 8080.0
BUILD_LIST 3
BUILD_MAP 2
BUILD_MAP 2
STORE_NAME nested_structure
POP_TOP None
LOAD_NAME nested_structure
LOAD_CONST "users"
BINARY_SUBSCR None
LOAD_CONST 0.0
BINARY_SUBSCR None
LOAD_CONST "name"
BINARY_SUBSCR None
STORE_NAME admin_name
POP_TOP None
LOAD_NAME nested_structure
LOAD_CONST "users"
BINARY_SUBSCR None
LOAD_CONST 0.0
BINARY_SUBSCR None
LOAD_CONST "permissions"
BINARY_SUBSCR None
LOAD_CONST 2.0
BINARY_SUBSCR None
STORE_NAME admin_permissions
POP_TOP None
LOAD_NAME nested_structure
LOAD_CONST "config"
BINARY_SUBSCR None
LOAD_CONST "servers"
BINARY_SUBSCR None
LOAD_CONST 0.0
BINARY_SUBSCR None
STORE_NAME first_server
POP_TOP None
LOAD_NAME nested_structure
LOAD_CONST "config"
BINARY_SUBSCR None
LOAD_CONST "ports"
BINARY_SUBSCR None
LOAD_CONST 1.0
BINARY_SUBSCR None
STORE_NAME https_port
POP_TOP None
LOAD_CONST "endpoint"
STORE_NAME prop_name
POP_TOP None
LOAD_CONST "api_key"
STORE_NAME key_name
POP_TOP None
LOAD_NAME config_dict
LOAD_NAME prop_name
BINARY_SUBSCR None
STORE_NAME dynamic_access1
POP_TOP None
LOAD_NAME config_dict
LOAD_NAME key_name
BINARY_SUBSCR None
STORE_NAME dynamic_access2
POP_TOP None
LOAD_CONST "api"
LOAD_CONST "_key"
BINARY_ADD None
STORE_NAME computed_key
POP_TOP None
IMPORT_NAME base64
PUSH_NULL None
PUSH_NULL None
LOAD_NAME base64
LOAD_ATTR b64encode
LOAD_CONST b"endpoint"
CALL_FUNCTION 1
LOAD_ATTR decode
CALL_FUNCTION 0
LOAD_CONST None
LOAD_CONST None
LOAD_CONST None
BINARY_OPERATION None
BINARY_SUBSCR None
STORE_NAME encoded_key
POP_TOP None
LOAD_NAME config_dict
LOAD_NAME computed_key
BINARY_SUBSCR None
STORE_NAME obfuscated_access
POP_TOP None
PUSH_NULL None
LOAD_NAME list
PUSH_NULL None
LOAD_NAME range
LOAD_CONST 0.0
LOAD_CONST 20.0
LOAD_CONST 2.0
CALL_FUNCTION 3
CALL_FUNCTION 1
STORE_NAME payload_list
POP_TOP None
LOAD_NAME payload_list
LOAD_CONST 5.0
LOAD_CONST 2.0
BINARY_ADD None
BINARY_SUBSCR None
STORE_NAME calculated_index
POP_TOP None
LOAD_NAME payload_list
LOAD_CONST 2.0
LOAD_CONST 2.0
BINARY_POWER None
BINARY_SUBSCR None
STORE_NAME expression_index
POP_TOP None
LOAD_NAME payload_list
LOAD_CONST 15.0
PUSH_NULL None
LOAD_NAME len
LOAD_NAME payload_list
CALL_FUNCTION 1
BINARY_MODULO None
BINARY_SUBSCR None
STORE_NAME modulo_index
POP_TOP None
LOAD_CONST "eval(base64.b64decode(payload))"
STORE_NAME malicious_string
POP_TOP None
LOAD_NAME malicious_string
LOAD_CONST 0.0
BINARY_SUBSCR None
STORE_NAME protocol_char
POP_TOP None
LOAD_NAME malicious_string
PUSH_NULL None
LOAD_NAME malicious_string
LOAD_ATTR find
LOAD_CONST "("
CALL_FUNCTION 1
BINARY_SUBSCR None
STORE_NAME paren_char
POP_TOP None
LOAD_NAME malicious_string
LOAD_CONST None
LOAD_CONST None
LOAD_CONST None
BINARY_OPERATION None
BINARY_SUBSCR None
STORE_NAME decode_part
POP_TOP None
LOAD_CONST 1.0
LOAD_CONST 2.0
LOAD_CONST 3.0
BUILD_LIST 3
LOAD_CONST 4.0
LOAD_CONST 5.0
LOAD_CONST 6.0
BUILD_LIST 3
LOAD_CONST 7.0
LOAD_CONST 8.0
LOAD_CONST 9.0
BUILD_LIST 3
BUILD_LIST 3
STORE_NAME matrix
POP_TOP None
LOAD_NAME matrix
LOAD_CONST 1.0
BINARY_SUBSCR None
LOAD_CONST 1.0
BINARY_SUBSCR None
STORE_NAME center_element
POP_TOP None
LOAD_NAME matrix
LOAD_CONST 0.0
BINARY_SUBSCR None
LOAD_CONST 0.0
BINARY_SUBSCR None
STORE_NAME corner_element
POP_TOP None
LOAD_NAME matrix
LOAD_CONST 1.0
UNARY_NEGATIVE None
BINARY_SUBSCR None
LOAD_CONST 1.0
UNARY_NEGATIVE None
BINARY_SUBSCR None
STORE_NAME last_row_last_col
POP_TOP None
LOAD_CONST "python"
LOAD_CONST "-c"
LOAD_CONST "import os; os.system('malicious')"
BUILD_TUPLE 3
STORE_NAME command_tuple
POP_TOP None
LOAD_NAME command_tuple
LOAD_CONST 0.0
BINARY_SUBSCR None
STORE_NAME interpreter
POP_TOP None
LOAD_NAME command_tuple
LOAD_CONST 1.0
BINARY_SUBSCR None
STORE_NAME flag
POP_TOP None
LOAD_NAME command_tuple
LOAD_CONST 2.0
BINARY_SUBSCR None
STORE_NAME command_payload
POP_TOP None
LOAD_CONST b"\x48\x65\x6c\x6c\x6f"
STORE_NAME byte_data
POP_TOP None
LOAD_NAME byte_data
LOAD_CONST 0.0
BINARY_SUBSCR None
STORE_NAME first_byte
POP_TOP None
LOAD_NAME byte_data
LOAD_CONST 1.0
BINARY_SUBSCR None
STORE_NAME second_byte
POP_TOP None
LOAD_NAME byte_data
LOAD_CONST None
LOAD_CONST None
LOAD_CONST None
BINARY_OPERATION None
BINARY_SUBSCR None
STORE_NAME byte_slice
POP_TOP None
IMPORT_NAME random
LOAD_CONST 2.0
STORE_NAME global_index
POP_TOP None
LOAD_NAME test_list
LOAD_NAME global_index
BINARY_SUBSCR None
STORE_NAME scoped_access
POP_TOP None
LOAD_NAME test_list
PUSH_NULL None
LOAD_NAME random
LOAD_ATTR randint
LOAD_CONST 0.0
PUSH_NULL None
LOAD_NAME len
LOAD_NAME test_list
CALL_FUNCTION 1
LOAD_CONST 1.0
BINARY_SUBTRACT None
CALL_FUNCTION 2
BINARY_SUBSCR None
STORE_NAME function_based_index
POP_TOP None
LOAD_NAME test_list
LOAD_CONST None
LOAD_CONST None
LOAD_CONST None
BINARY_OPERATION None
BINARY_SUBSCR None
STORE_NAME complex_slice1
POP_TOP None
LOAD_NAME test_list
LOAD_CONST None
LOAD_CONST None
LOAD_CONST None
BINARY_OPERATION None
BINARY_SUBSCR None
STORE_NAME complex_slice2
POP_TOP None
LOAD_NAME test_list
LOAD_CONST None
LOAD_CONST None
LOAD_CONST None
BINARY_OPERATION None
BINARY_SUBSCR None
STORE_NAME complex_slice3
POP_TOP None
PUSH_NULL None
LOAD_NAME list
PUSH_NULL None
LOAD_NAME config_dict
LOAD_ATTR keys
CALL_FUNCTION 0
CALL_FUNCTION 1
STORE_NAME dict_keys
POP_TOP None
PUSH_NULL None
LOAD_NAME list
PUSH_NULL None
LOAD_NAME config_dict
LOAD_ATTR values
CALL_FUNCTION 0
CALL_FUNCTION 1
STORE_NAME dict_values
POP_TOP None
LOAD_NAME dict_keys
LOAD_CONST 0.0
BINARY_SUBSCR None
STORE_NAME first_key
POP_TOP None
LOAD_NAME dict_values
LOAD_CONST 0.0
BINARY_SUBSCR None
STORE_NAME first_value
POP_TOP None
PUSH_NULL None
LOAD_NAME print
LOAD_CONST "9.18. BINARY_SUBSCR Test Cases: PASSED"
CALL_FUNCTION 1
POP_TOP None
BUILD_MAP 0
STORE_NAME store_obj
POP_TOP None
BUILD_LIST 0
STORE_NAME store_arr
POP_TOP None
LOAD_CONST "inner"
BUILD_MAP 0
BUILD_MAP 1
STORE_NAME store_nested
POP_TOP None
LOAD_CONST "value1"
LOAD_NAME store_obj
LOAD_CONST "key1"
STORE_SUBSCR None
POP_TOP None
LOAD_CONST "value2"
LOAD_NAME store_obj
LOAD_CONST "key2"
STORE_SUBSCR None
POP_TOP None
LOAD_CONST """value3"""
LOAD_NAME store_obj
LOAD_CONST """key3"""
STORE_SUBSCR None
POP_TOP None
LOAD_CONST "dynamicKey"
STORE_NAME store_key
POP_TOP None
LOAD_CONST "dynamicValue"
LOAD_NAME store_obj
LOAD_NAME store_key
STORE_SUBSCR None
POP_TOP None
PUSH_NULL None
LOAD_NAME store_arr
LOAD_ATTR extend
LOAD_CONST None
LOAD_CONST None
LOAD_CONST None
BUILD_LIST 3
CALL_FUNCTION 1
POP_TOP None
LOAD_CONST "first"
LOAD_NAME store_arr
LOAD_CONST 0.0
STORE_SUBSCR None
POP_TOP None
LOAD_CONST "second"
LOAD_NAME store_arr
LOAD_CONST 1.0
STORE_SUBSCR None
POP_TOP None
LOAD_CONST "third"
LOAD_NAME store_arr
LOAD_CONST 2.0
STORE_SUBSCR None
POP_TOP None
LOAD_CONST "computed"
STORE_NAME store_prefix
POP_TOP None
LOAD_CONST "computed value"
LOAD_NAME store_obj
LOAD_NAME store_prefix
LOAD_CONST "_key"
BINARY_ADD None
STORE_SUBSCR None
POP_TOP None
LOAD_CONST "template value"
LOAD_NAME store_obj
LOAD_NAME store_prefix
FORMAT_VALUE None
LOAD_CONST _template
BUILD_STRING 2
STORE_SUBSCR None
POP_TOP None
LOAD_CONST "deeply nested"
LOAD_NAME store_nested
LOAD_CONST "inner"
BINARY_SUBSCR None
LOAD_CONST "deep"
STORE_SUBSCR None
POP_TOP None
MAKE_FUNCTION get_store_key_ref_69
STORE_NAME get_store_key
LOAD_CONST "from function"
LOAD_NAME store_obj
PUSH_NULL None
LOAD_NAME get_store_key
CALL_FUNCTION 0
STORE_SUBSCR None
POP_TOP None
LOAD_CONST "numeric expression"
LOAD_NAME store_obj
LOAD_CONST 1.0
LOAD_CONST 2.0
BINARY_ADD None
STORE_SUBSCR None
POP_TOP None
LOAD_CONST "method call key"
LOAD_NAME store_obj
PUSH_NULL None
LOAD_NAME store_key
LOAD_ATTR upper
CALL_FUNCTION 0
STORE_SUBSCR None
POP_TOP None
LOAD_CONST 0.0
STORE_NAME store_counter
POP_TOP None
LOAD_CONST "with side effect"
LOAD_NAME store_obj
LOAD_NAME store_counter
STORE_SUBSCR None
POP_TOP None
LOAD_NAME store_counter
LOAD_CONST 1.0
BINARY_OPERATION None
STORE_NAME store_counter
POP_TOP None
LOAD_CONST "chained"
LOAD_NAME store_obj
LOAD_CONST "b"
STORE_SUBSCR None
LOAD_NAME store_obj
LOAD_CONST "a"
STORE_SUBSCR None
POP_TOP None
LOAD_CONST 1.0
LOAD_CONST 2.0
LOAD_CONST 3.0
LOAD_CONST 4.0
LOAD_CONST 5.0
BUILD_LIST 5
STORE_NAME store_list
POP_TOP None
LOAD_CONST 10.0
LOAD_CONST 20.0
BUILD_LIST 2
LOAD_NAME store_list
LOAD_CONST 1.0
LOAD_CONST 3.0
STORE_SUBSCR None
POP_TOP None
LOAD_CONST 100.0
LOAD_CONST 200.0
LOAD_CONST 300.0
BUILD_LIST 3
LOAD_NAME store_list
LOAD_CONST 2.0
STORE_SUBSCR None
POP_TOP None
PUSH_NULL None
LOAD_NAME print
LOAD_CONST "9.19. STORE_SUBSCR Test Cases: PASSED"
CALL_FUNCTION 1
POP_TOP None
PUSH_NULL None
LOAD_NAME print
LOAD_CONST "\n--- Python Compiler Test Suite: Finished ---"
CALL_FUNCTION 1
POP_TOP None
PUSH_NULL None
LOAD_NAME print
LOAD_CONST "--- All tests completed. Check output for any FAILED messages. ---"
CALL_FUNCTION 1
POP_TOP None
LOAD_CONST "os"
STORE_GLOBAL module_name
POP_TOP None
PUSH_NULL None
LOAD_GLOBAL __import__
LOAD_GLOBAL module_name
CALL_FUNCTION 1
STORE_GLOBAL imported_os
POP_TOP None
PUSH_NULL None
LOAD_GLOBAL getattr
LOAD_GLOBAL imported_os
LOAD_CONST "system"
CALL_FUNCTION 2
STORE_GLOBAL getattr_call
POP_TOP None
PUSH_NULL None
LOAD_GLOBAL getattr
LOAD_GLOBAL __builtins__
LOAD_CONST "exec"
CALL_FUNCTION 2
STORE_GLOBAL exec_func
POP_TOP None
PUSH_NULL None
LOAD_GLOBAL getattr
LOAD_GLOBAL __builtins__
LOAD_CONST "eval"
CALL_FUNCTION 2
STORE_GLOBAL eval_func
POP_TOP None
RETURN_VALUE None
PUSH_NULL None
LOAD_GLOBAL print
LOAD_CONST "Entering context"
CALL_FUNCTION 1
POP_TOP None
LOAD_CONST "Hello from with"
RETURN_VALUE None
PUSH_NULL None
LOAD_GLOBAL print
LOAD_CONST "Exiting context"
CALL_FUNCTION 1
POP_TOP None
RETURN_VALUE None
MAKE_FUNCTION __enter___ref_1
STORE_NAME __enter__
MAKE_FUNCTION __exit___ref_2
STORE_NAME __exit__
LOAD_CONST Hello, 
LOAD_PARAM name
FORMAT_VALUE None
LOAD_CONST !
BUILD_STRING 3
RETURN_VALUE None
LOAD_PARAM a
LOAD_PARAM b
BINARY_ADD None
LOAD_PARAM c
BINARY_ADD None
RETURN_VALUE None
LOAD_PARAM args
LOAD_PARAM kwargs
RETURN_VALUE None
LOAD_PARAM x
LOAD_PARAM y
BINARY_MULTIPLY None
RETURN_VALUE None
LOAD_GLOBAL x
LOAD_CONST 1.0
BINARY_OPERATION None
STORE_GLOBAL x
POP_TOP None
LOAD_GLOBAL x
RETURN_VALUE None
LOAD_CONST 10.0
STORE_GLOBAL x
POP_TOP None
MAKE_FUNCTION inner_func_ref_8
STORE_GLOBAL inner_func
LOAD_GLOBAL inner_func
RETURN_VALUE None
LOAD_CONST 200.0
STORE_GLOBAL global_var
POP_TOP None
RETURN_VALUE None
LOAD_PARAM instance_variable
LOAD_PARAM self
STORE_ATTR instance_variable
POP_TOP None
RETURN_VALUE None
LOAD_PARAM self
LOAD_ATTR instance_variable
RETURN_VALUE None
LOAD_PARAM cls
LOAD_ATTR class_variable
RETURN_VALUE None
LOAD_CONST "static"
RETURN_VALUE None
LOAD_CONST 10.0
STORE_NAME class_variable
POP_TOP None
MAKE_FUNCTION __init___ref_11
STORE_NAME __init__
MAKE_FUNCTION instance_method_ref_12
STORE_NAME instance_method
MAKE_FUNCTION class_method_ref_13
STORE_NAME class_method
MAKE_FUNCTION static_method_ref_14
STORE_NAME static_method
LOAD_CONST "A"
RETURN_VALUE None
MAKE_FUNCTION method_a_ref_16
STORE_NAME method_a
LOAD_CONST "B"
RETURN_VALUE None
MAKE_FUNCTION method_b_ref_18
STORE_NAME method_b
LOAD_CONST "C"
RETURN_VALUE None
MAKE_FUNCTION method_c_ref_20
STORE_NAME method_c
LOAD_PARAM x
LOAD_PARAM self
STORE_ATTR x
POP_TOP None
LOAD_PARAM y
LOAD_PARAM self
STORE_ATTR y
POP_TOP None
RETURN_VALUE None
PUSH_NULL None
LOAD_GLOBAL Vector
LOAD_PARAM self
LOAD_ATTR x
LOAD_PARAM other
LOAD_ATTR x
BINARY_ADD None
LOAD_PARAM self
LOAD_ATTR y
LOAD_PARAM other
LOAD_ATTR y
BINARY_ADD None
CALL_FUNCTION 2
RETURN_VALUE None
LOAD_CONST Vector(
LOAD_PARAM self
LOAD_ATTR x
FORMAT_VALUE None
LOAD_CONST , 
LOAD_PARAM self
LOAD_ATTR y
FORMAT_VALUE None
LOAD_CONST )
BUILD_STRING 5
RETURN_VALUE None
LOAD_CONST 2.0
RETURN_VALUE None
LOAD_PARAM index
LOAD_CONST 0.0
COMPARE_OP None
POP_JUMP_IF_FALSE 7
LOAD_PARAM self
LOAD_ATTR x
RETURN_VALUE None
LOAD_PARAM index
LOAD_CONST 1.0
COMPARE_OP None
POP_JUMP_IF_FALSE 7
LOAD_PARAM self
LOAD_ATTR y
RETURN_VALUE None
LOAD_GLOBAL IndexError
BINARY_OPERATION None
RETURN_VALUE None
MAKE_FUNCTION __init___ref_22
STORE_NAME __init__
MAKE_FUNCTION __add___ref_23
STORE_NAME __add__
MAKE_FUNCTION __repr___ref_24
STORE_NAME __repr__
MAKE_FUNCTION __len___ref_25
STORE_NAME __len__
MAKE_FUNCTION __getitem___ref_26
STORE_NAME __getitem__
LOAD_PARAM radius
LOAD_PARAM self
STORE_ATTR _radius
POP_TOP None
RETURN_VALUE None
LOAD_PARAM self
LOAD_ATTR _radius
RETURN_VALUE None
LOAD_PARAM value
LOAD_CONST 0.0
COMPARE_OP None
POP_JUMP_IF_FALSE 9
PUSH_NULL None
LOAD_GLOBAL ValueError
LOAD_CONST "Radius cannot be negative"
CALL_FUNCTION 1
BINARY_OPERATION None
LOAD_PARAM value
LOAD_PARAM self
STORE_ATTR _radius
POP_TOP None
RETURN_VALUE None
LOAD_CONST 3.14
LOAD_PARAM self
LOAD_ATTR _radius
LOAD_CONST 2.0
BINARY_POWER None
BINARY_MULTIPLY None
RETURN_VALUE None
MAKE_FUNCTION __init___ref_28
STORE_NAME __init__
MAKE_FUNCTION radius_ref_29
STORE_NAME radius
MAKE_FUNCTION radius_ref_30
STORE_NAME radius
MAKE_FUNCTION area_ref_31
STORE_NAME area
PUSH_NULL None
LOAD_GLOBAL print
LOAD_CONST "Something is happening before the function is called."
CALL_FUNCTION 1
POP_TOP None
PUSH_NULL None
LOAD_GLOBAL func
LOAD_PARAM args
LOAD_PARAM kwargs
CALL_FUNCTION 0
STORE_GLOBAL result
POP_TOP None
PUSH_NULL None
LOAD_GLOBAL print
LOAD_CONST "Something is happening after the function is called."
CALL_FUNCTION 1
POP_TOP None
LOAD_GLOBAL result
RETURN_VALUE None
MAKE_FUNCTION wrapper_ref_33
STORE_GLOBAL wrapper
LOAD_GLOBAL wrapper
RETURN_VALUE None
LOAD_CONST "Whee!"
RETURN_VALUE None
PUSH_NULL None
LOAD_GLOBAL range
LOAD_PARAM n
CALL_FUNCTION 1
LOAD_CONST None
YIELD_VALUE None
POP_TOP None
RETURN_VALUE None
PUSH_NULL None
LOAD_GLOBAL asyncio
LOAD_ATTR sleep
LOAD_CONST 0.01
CALL_FUNCTION 1
AWAIT_EXPRESSION None
POP_TOP None
LOAD_CONST "Coroutine finished"
RETURN_VALUE None
PUSH_NULL None
LOAD_GLOBAL my_coroutine
CALL_FUNCTION 0
AWAIT_EXPRESSION None
STORE_GLOBAL result
POP_TOP None
PUSH_NULL None
LOAD_GLOBAL print
LOAD_CONST "6.3. Coroutines (async/await): PASSED"
CALL_FUNCTION 1
POP_TOP None
RETURN_VALUE None
LOAD_CONST "Hello from metaclass"
LOAD_PARAM dct
LOAD_CONST "new_attribute"
STORE_SUBSCR None
POP_TOP None
PUSH_NULL None
PUSH_NULL None
LOAD_GLOBAL super
CALL_FUNCTION 0
LOAD_ATTR __new__
LOAD_PARAM cls
LOAD_PARAM name
LOAD_PARAM bases
LOAD_PARAM dct
CALL_FUNCTION 4
RETURN_VALUE None
MAKE_FUNCTION __new___ref_39
STORE_NAME __new__

LOAD_PARAM name
FORMAT_VALUE None
LOAD_CONST  is 
LOAD_PARAM age
FORMAT_VALUE None
LOAD_CONST  years old.
BUILD_STRING 4
RETURN_VALUE None

LOAD_CONST ...
RETURN_VALUE None
LOAD_PARAM x
LOAD_CONST 2.0
BINARY_MULTIPLY None
RETURN_VALUE None
LOAD_CONST "context_value"
RETURN_VALUE None
LOAD_CONST False
RETURN_VALUE None
MAKE_FUNCTION __enter___ref_46
STORE_NAME __enter__
MAKE_FUNCTION __exit___ref_47
STORE_NAME __exit__
RETURN_VALUE None
PUSH_NULL None
LOAD_GLOBAL ValueError
LOAD_CONST "Test error"
CALL_FUNCTION 1
BINARY_OPERATION None
RETURN_VALUE None
LOAD_CONST "modified"
STORE_GLOBAL global_var
POP_TOP None
RETURN_VALUE None
LOAD_CONST "inner"
STORE_GLOBAL nonlocal_var
POP_TOP None
RETURN_VALUE None
LOAD_CONST "outer"
STORE_GLOBAL nonlocal_var
POP_TOP None
MAKE_FUNCTION inner_ref_52
STORE_GLOBAL inner
PUSH_NULL None
LOAD_GLOBAL inner
CALL_FUNCTION 0
POP_TOP None
LOAD_GLOBAL nonlocal_var
RETURN_VALUE None
LOAD_GLOBAL simple_global
RETURN_VALUE None
LOAD_GLOBAL simple_global
LOAD_CONST 1.0
BINARY_ADD None
STORE_GLOBAL simple_global
POP_TOP None
LOAD_CONST 100.0
STORE_GLOBAL simple_global
POP_TOP None
RETURN_VALUE None
LOAD_GLOBAL global_x
LOAD_CONST 2.0
BINARY_MULTIPLY None
STORE_GLOBAL global_x
POP_TOP None
LOAD_GLOBAL global_y
LOAD_GLOBAL global_x
BINARY_ADD None
STORE_GLOBAL global_y
POP_TOP None
LOAD_GLOBAL global_x
LOAD_GLOBAL global_y
BINARY_ADD None
LOAD_GLOBAL global_z
BINARY_ADD None
STORE_GLOBAL global_z
POP_TOP None
LOAD_GLOBAL global_x
LOAD_GLOBAL global_y
LOAD_GLOBAL global_z
RETURN_VALUE None
LOAD_CONST "I am local"
STORE_GLOBAL local_var
POP_TOP None
LOAD_GLOBAL local_var
STORE_GLOBAL temp
POP_TOP None
LOAD_GLOBAL mixed_var
STORE_GLOBAL global_temp
POP_TOP None
LOAD_CONST "Modified by function"
STORE_GLOBAL mixed_var
POP_TOP None
LOAD_CONST "Modified locally"
STORE_GLOBAL local_var
POP_TOP None
LOAD_GLOBAL local_var
LOAD_GLOBAL mixed_var
RETURN_VALUE None
LOAD_GLOBAL context_global
LOAD_CONST "key"
BINARY_SUBSCR None
STORE_GLOBAL value
POP_TOP None
PUSH_NULL None
LOAD_GLOBAL context_global
LOAD_ATTR keys
CALL_FUNCTION 0
STORE_GLOBAL keys
POP_TOP None
LOAD_CONST "new_key"
LOAD_CONST "new_value"
LOAD_CONST "count"
LOAD_CONST 42.0
BUILD_MAP 2
STORE_GLOBAL context_global
POP_TOP None
LOAD_GLOBAL context_global
POP_JUMP_IF_FALSE 11
LOAD_GLOBAL context_global
LOAD_CONST "count"
BINARY_SUBSCR None
LOAD_CONST 1.0
BINARY_ADD None
LOAD_GLOBAL context_global
LOAD_CONST "count"
STORE_SUBSCR None
POP_TOP None
RETURN_VALUE None
LOAD_CONST "I am a global function"
RETURN_VALUE None

LOAD_GLOBAL global_function
STORE_GLOBAL func_ref
POP_TOP None
LOAD_GLOBAL GlobalClass
STORE_GLOBAL class_ref
POP_TOP None
PUSH_NULL None
LOAD_GLOBAL global_function
CALL_FUNCTION 0
STORE_GLOBAL result
POP_TOP None
PUSH_NULL None
LOAD_GLOBAL GlobalClass
CALL_FUNCTION 0
STORE_GLOBAL instance
POP_TOP None
LOAD_GLOBAL func_ref
LOAD_GLOBAL class_ref
LOAD_GLOBAL result
LOAD_GLOBAL instance
RETURN_VALUE None
LOAD_GLOBAL outer_global
STORE_GLOBAL temp1
POP_TOP None
LOAD_GLOBAL inner_var
STORE_GLOBAL temp2
POP_TOP None
LOAD_CONST "modified by inner"
STORE_GLOBAL outer_global
POP_TOP None
LOAD_CONST "modified by inner"
STORE_GLOBAL inner_var
POP_TOP None
RETURN_VALUE None
LOAD_CONST "inner"
STORE_GLOBAL inner_var
POP_TOP None
MAKE_FUNCTION inner_with_global_ref_62
STORE_GLOBAL inner_with_global
PUSH_NULL None
LOAD_GLOBAL inner_with_global
CALL_FUNCTION 0
POP_TOP None
LOAD_GLOBAL inner_var
LOAD_GLOBAL outer_global
RETURN_VALUE None
BUILD_LIST 0
LOAD_GLOBAL comp_global
GET_ITER None
FOR_ITER 10
STORE_NAME x
LOAD_GLOBAL x
LOAD_CONST 2.0
BINARY_MULTIPLY None
LIST_APPEND 1
JUMP_FORWARD 3
STORE_GLOBAL doubled
POP_TOP None
LOAD_GLOBAL comp_global
GET_ITER None
FOR_ITER 8
STORE_NAME x
LOAD_GLOBAL x
LOAD_CONST 2.0
BINARY_POWER None
JUMP_FORWARD 2
STORE_GLOBAL gen
POP_TOP None
PUSH_NULL None
LOAD_GLOBAL list
PUSH_NULL None
LOAD_GLOBAL range
LOAD_CONST 10.0
CALL_FUNCTION 1
CALL_FUNCTION 1
STORE_GLOBAL comp_global
POP_TOP None
LOAD_GLOBAL doubled
PUSH_NULL None
LOAD_GLOBAL list
LOAD_GLOBAL gen
CALL_FUNCTION 1
RETURN_VALUE None
LOAD_CONST "modified local"
STORE_GLOBAL shadow_var
POP_TOP None
RETURN_VALUE None
LOAD_CONST "modified global"
STORE_GLOBAL shadow_var
POP_TOP None
RETURN_VALUE None
LOAD_CONST "local shadow"
STORE_GLOBAL shadow_var
POP_TOP None
MAKE_FUNCTION inner_shadow_ref_65
STORE_GLOBAL inner_shadow
MAKE_FUNCTION inner_global_shadow_ref_66
STORE_GLOBAL inner_global_shadow
PUSH_NULL None
LOAD_GLOBAL inner_shadow
CALL_FUNCTION 0
POP_TOP None
LOAD_GLOBAL shadow_var
STORE_GLOBAL local_result
POP_TOP None
PUSH_NULL None
LOAD_GLOBAL inner_global_shadow
CALL_FUNCTION 0
POP_TOP None
LOAD_GLOBAL local_result
RETURN_VALUE None
LOAD_GLOBAL type
STORE_GLOBAL current
POP_TOP None
LOAD_CONST "modified type"
STORE_GLOBAL type
POP_TOP None
LOAD_GLOBAL __builtins__
LOAD_ATTR type
STORE_GLOBAL actual_type
POP_TOP None
LOAD_GLOBAL current
LOAD_GLOBAL actual_type
RETURN_VALUE None
LOAD_CONST "funcKey"
RETURN_VALUE None